kinetix/base.py
kinetix/parser.py
kinetix/runner.py
kinetix-0.1.0.dist-info/entry_points.txt
kinetix-0.1.0.dist-info/LICENSE
kinetix-0.1.0.dist-info/WHEEL
kinetix-0.1.0.dist-info/METADATA
kinetix-0.1.0.dist-info/RECORD
