Metadata-Version: 2.1
Name: kinetix
Version: 0.1.0
Summary: A simple lightweight library for simulating and plotting enzyme kinetics
License: MIT
Author: Lior Zimmerman
Author-email: zimmerman.lior@gmail.com
Classifier: License :: OSI Approved :: MIT License
Classifier: Programming Language :: Python :: 2
Classifier: Programming Language :: Python :: 2.7
Classifier: Programming Language :: Python :: 3
Classifier: Programming Language :: Python :: 3.4
Classifier: Programming Language :: Python :: 3.5
Classifier: Programming Language :: Python :: 3.6
Classifier: Programming Language :: Python :: 3.7
Classifier: Programming Language :: Python :: 3.8
Classifier: Programming Language :: Python :: 3.9
Classifier: Programming Language :: Python :: 3.10
Classifier: Programming Language :: Python :: 3.11
Classifier: Topic :: Scientific/Engineering :: Bio-Informatics
Requires-Dist: matplotlib (>=3.1.3)
Requires-Dist: networkx (>=2.5)
Requires-Dist: pandas (>=1.1.5)
Requires-Dist: seaborn (>=0.12.0)
